skeit/__init__.py
skeit/eit.py
scikit_eit-0.0.1.dist-info/METADATA
scikit_eit-0.0.1.dist-info/WHEEL
scikit_eit-0.0.1.dist-info/licenses/LICENSE
scikit_eit-0.0.1.dist-info/RECORD
