Metadata-Version: 2.1
Name: scikit-eit
Version: 0.0.1
Summary: A Python package for electrical impedance tomography.
Project-URL: Homepage, https://github.com/USNavalResearchLaboratory/scikit-eit
Project-URL: Bug Tracker, https://github.com/USNavalResearchLaboratory/scikit-eit/issues
Author-email: George Gatling <george.gatling@nrl.navy.mil>
License-File: LICENSE
Classifier: License :: OSI Approved :: MIT License
Classifier: Operating System :: OS Independent
Classifier: Programming Language :: Python :: 3
Requires-Python: >=3.7
